hplib/__init__.py
hplib/_version.py
hplib/hplib.py
hplib/hplib_database.csv
hplib/hplib_database.py
hplib/hplib_database_all.csv
hplib/same_built_type.pkl
hplib-1.9.dist-info/LICENSE
hplib-1.9.dist-info/METADATA
hplib-1.9.dist-info/WHEEL
hplib-1.9.dist-info/top_level.txt
hplib-1.9.dist-info/RECORD
