Metadata-Version: 2.1
Name: hplib
Version: 1.9
Summary: Database and code to simulate heat pumps
Home-page: https://github.com/RE-Lab-Projects/hplib
Author: RE-Lab HS-Emden-Leer
License: MIT
Platform: unix
Platform: linux
Platform: osx
Platform: cygwin
Platform: win32
Classifier: Programming Language :: Python :: 3
Classifier: Programming Language :: Python :: 3 :: Only
Classifier: Programming Language :: Python :: 3.6
Classifier: Programming Language :: Python :: 3.7
Classifier: Programming Language :: Python :: 3.8
Classifier: Programming Language :: Python :: 3.9
License-File: LICENSE
Requires-Dist: numpy (>=1.16.0)
Requires-Dist: pandas (>=0.22.0)
Requires-Dist: scipy
